[
  {
    "kanji": "引",
    "grade": 2,
    "kyoiku_index": 81,
    "onyomi": [
      "イン"
    ],
    "kunyomi": [
      "ひく",
      "ひ"
    ],
    "meaning_en": "",
    "meaning_hira": "",
    "label": "[ひ]く"
  },
  {
    "kanji": "羽",
    "grade": 2,
    "kyoiku_index": 82,
    "onyomi": [
      "ウ"
    ],
    "kunyomi": [
      "は",
      "わ",
      "はね"
    ],
    "meaning_en": "",
    "meaning_hira": "",
    "label": "はね"
  },
  {
    "kanji": "雲",
    "grade": 2,
    "kyoiku_index": 83,
    "onyomi": [
      "ウン"
    ],
    "kunyomi": [
      "くも"
    ],
    "meaning_en": "",
    "meaning_hira": "",
    "label": "くも"
  },
  {
    "kanji": "園",
    "grade": 2,
    "kyoiku_index": 84,
    "onyomi": [
      "エン"
    ],
    "kunyomi": [
      "その"
    ],
    "meaning_en": "",
    "meaning_hira": "",
    "label": "えん"
  },
  {
    "kanji": "遠",
    "grade": 2,
    "kyoiku_index": 85,
    "onyomi": [
      "エン",
      "オン"
    ],
    "kunyomi": [
      "とおい",
      "とお"
    ],
    "meaning_en": "",
    "meaning_hira": "",
    "label": "[とお]い"
  },
  {
    "kanji": "何",
    "grade": 2,
    "kyoiku_index": 86,
    "onyomi": [
      "カ"
    ],
    "kunyomi": [
      "なに",
      "なん"
    ],
    "meaning_en": "",
    "meaning_hira": "",
    "label": "なん"
  },
  {
    "kanji": "科",
    "grade": 2,
    "kyoiku_index": 87,
    "onyomi": [
      "カ"
    ],
    "kunyomi": [],
    "meaning_en": "",
    "meaning_hira": "",
    "label": "とが"
  },
  {
    "kanji": "夏",
    "grade": 2,
    "kyoiku_index": 88,
    "onyomi": [
      "カ",
      "ガ",
      "ゲ"
    ],
    "kunyomi": [
      "なつ"
    ],
    "meaning_en": "",
    "meaning_hira": "",
    "label": "なつ"
  },
  {
    "kanji": "家",
    "grade": 2,
    "kyoiku_index": 89,
    "onyomi": [
      "カ",
      "ケ"
    ],
    "kunyomi": [
      "いえ",
      "や",
      "うち"
    ],
    "meaning_en": "",
    "meaning_hira": "",
    "label": "か"
  },
  {
    "kanji": "歌",
    "grade": 2,
    "kyoiku_index": 90,
    "onyomi": [
      "カ"
    ],
    "kunyomi": [
      "うた"
    ],
    "meaning_en": "",
    "meaning_hira": "",
    "label": "うた"
  },
  {
    "kanji": "画",
    "grade": 2,
    "kyoiku_index": 91,
    "onyomi": [
      "ガ",
      "カク",
      "エ",
      "カイ"
    ],
    "kunyomi": [
      "えがく",
      "えが",
      "かぎ",
      "はかりごと",
      "はか"
    ],
    "meaning_en": "",
    "meaning_hira": "",
    "label": "かく"
  },
  {
    "kanji": "回",
    "grade": 2,
    "kyoiku_index": 92,
    "onyomi": [
      "カイ",
      "エ"
    ],
    "kunyomi": [
      "まわる",
      "まわ",
      "もとお",
      "か"
    ],
    "meaning_en": "",
    "meaning_hira": "",
    "label": "かい"
  },
  {
    "kanji": "会",
    "grade": 2,
    "kyoiku_index": 93,
    "onyomi": [
      "カイ",
      "エ"
    ],
    "kunyomi": [
      "あう",
      "あ",
      "あつ"
    ],
    "meaning_en": "",
    "meaning_hira": "",
    "label": "え"
  },
  {
    "kanji": "海",
    "grade": 2,
    "kyoiku_index": 94,
    "onyomi": [
      "カイ"
    ],
    "kunyomi": [
      "うみ"
    ],
    "meaning_en": "",
    "meaning_hira": "",
    "label": "うみ"
  },
  {
    "kanji": "絵",
    "grade": 2,
    "kyoiku_index": 95,
    "onyomi": [
      "カイ",
      "エ"
    ],
    "kunyomi": [],
    "meaning_en": "",
    "meaning_hira": "",
    "label": "え"
  },
  {
    "kanji": "外",
    "grade": 2,
    "kyoiku_index": 96,
    "onyomi": [
      "ガイ",
      "ゲ"
    ],
    "kunyomi": [
      "そと",
      "はず",
      "ほか"
    ],
    "meaning_en": "",
    "meaning_hira": "",
    "label": "そと"
  },
  {
    "kanji": "角",
    "grade": 2,
    "kyoiku_index": 97,
    "onyomi": [
      "カク"
    ],
    "kunyomi": [
      "かど",
      "つの"
    ],
    "meaning_en": "",
    "meaning_hira": "",
    "label": "すみ"
  },
  {
    "kanji": "楽",
    "grade": 2,
    "kyoiku_index": 98,
    "onyomi": [
      "ガク",
      "ラク",
      "ゴウ"
    ],
    "kunyomi": [
      "たのしい",
      "たの",
      "この"
    ],
    "meaning_en": "",
    "meaning_hira": "",
    "label": "らく"
  },
  {
    "kanji": "活",
    "grade": 2,
    "kyoiku_index": 99,
    "onyomi": [
      "カツ"
    ],
    "kunyomi": [
      "いきる",
      "い"
    ],
    "meaning_en": "",
    "meaning_hira": "",
    "label": "かつ"
  },
  {
    "kanji": "間",
    "grade": 2,
    "kyoiku_index": 100,
    "onyomi": [
      "カン",
      "ケン"
    ],
    "kunyomi": [
      "あいだ",
      "ま",
      "あい"
    ],
    "meaning_en": "",
    "meaning_hira": "",
    "label": "けん"
  },
  {
    "kanji": "丸",
    "grade": 2,
    "kyoiku_index": 101,
    "onyomi": [
      "ガン"
    ],
    "kunyomi": [
      "まる"
    ],
    "meaning_en": "",
    "meaning_hira": "",
    "label": "まる"
  },
  {
    "kanji": "岩",
    "grade": 2,
    "kyoiku_index": 102,
    "onyomi": [
      "ガン"
    ],
    "kunyomi": [
      "いわ"
    ],
    "meaning_en": "",
    "meaning_hira": "",
    "label": "いわ"
  },
  {
    "kanji": "顔",
    "grade": 2,
    "kyoiku_index": 103,
    "onyomi": [
      "ガン"
    ],
    "kunyomi": [
      "かお"
    ],
    "meaning_en": "",
    "meaning_hira": "",
    "label": "かお"
  },
  {
    "kanji": "汽",
    "grade": 2,
    "kyoiku_index": 104,
    "onyomi": [
      "キ"
    ],
    "kunyomi": [],
    "meaning_en": "",
    "meaning_hira": "",
    "label": "[き]"
  },
  {
    "kanji": "記",
    "grade": 2,
    "kyoiku_index": 105,
    "onyomi": [
      "キ"
    ],
    "kunyomi": [
      "しるす",
      "しる"
    ],
    "meaning_en": "",
    "meaning_hira": "",
    "label": "き"
  },
  {
    "kanji": "帰",
    "grade": 2,
    "kyoiku_index": 106,
    "onyomi": [
      "キ"
    ],
    "kunyomi": [
      "かえる",
      "かえ",
      "おく",
      "とつ"
    ],
    "meaning_en": "",
    "meaning_hira": "",
    "label": "[かえ]る"
  },
  {
    "kanji": "弓",
    "grade": 2,
    "kyoiku_index": 107,
    "onyomi": [
      "キュウ"
    ],
    "kunyomi": [
      "ゆみ"
    ],
    "meaning_en": "",
    "meaning_hira": "",
    "label": "ゆみ"
  },
  {
    "kanji": "牛",
    "grade": 2,
    "kyoiku_index": 108,
    "onyomi": [
      "ギュウ"
    ],
    "kunyomi": [
      "うし"
    ],
    "meaning_en": "",
    "meaning_hira": "",
    "label": "うし"
  },
  {
    "kanji": "魚",
    "grade": 2,
    "kyoiku_index": 109,
    "onyomi": [
      "ギョ"
    ],
    "kunyomi": [
      "うお",
      "さかな"
    ],
    "meaning_en": "",
    "meaning_hira": "",
    "label": "さかな"
  },
  {
    "kanji": "京",
    "grade": 2,
    "kyoiku_index": 110,
    "onyomi": [
      "キョウ",
      "ケイ",
      "キン"
    ],
    "kunyomi": [
      "みやこ"
    ],
    "meaning_en": "",
    "meaning_hira": "",
    "label": "きょう"
  },
  {
    "kanji": "強",
    "grade": 2,
    "kyoiku_index": 111,
    "onyomi": [
      "キョウ",
      "ゴウ"
    ],
    "kunyomi": [
      "つよい",
      "つよ",
      "し",
      "こわ"
    ],
    "meaning_en": "",
    "meaning_hira": "",
    "label": "きょう"
  },
  {
    "kanji": "教",
    "grade": 2,
    "kyoiku_index": 112,
    "onyomi": [
      "キョウ"
    ],
    "kunyomi": [
      "おしえる",
      "おし",
      "おそ"
    ],
    "meaning_en": "",
    "meaning_hira": "",
    "label": "きょう"
  },
  {
    "kanji": "近",
    "grade": 2,
    "kyoiku_index": 113,
    "onyomi": [
      "キン",
      "コン"
    ],
    "kunyomi": [
      "ちかい",
      "ちか"
    ],
    "meaning_en": "",
    "meaning_hira": "",
    "label": "[ちか]い"
  },
  {
    "kanji": "兄",
    "grade": 2,
    "kyoiku_index": 114,
    "onyomi": [
      "ケイ",
      "キョウ"
    ],
    "kunyomi": [
      "あに"
    ],
    "meaning_en": "",
    "meaning_hira": "",
    "label": "けい"
  },
  {
    "kanji": "形",
    "grade": 2,
    "kyoiku_index": 115,
    "onyomi": [
      "ケイ",
      "ギョウ"
    ],
    "kunyomi": [
      "かた",
      "かたち",
      "なり"
    ],
    "meaning_en": "",
    "meaning_hira": "",
    "label": "かたち"
  },
  {
    "kanji": "計",
    "grade": 2,
    "kyoiku_index": 116,
    "onyomi": [
      "ケイ"
    ],
    "kunyomi": [
      "はかる",
      "はか"
    ],
    "meaning_en": "",
    "meaning_hira": "",
    "label": "はか"
  },
  {
    "kanji": "元",
    "grade": 2,
    "kyoiku_index": 117,
    "onyomi": [
      "ゲン",
      "ガン"
    ],
    "kunyomi": [
      "もと"
    ],
    "meaning_en": "",
    "meaning_hira": "",
    "label": "ゆあん"
  },
  {
    "kanji": "言",
    "grade": 2,
    "kyoiku_index": 118,
    "onyomi": [
      "ゲン",
      "ゴン"
    ],
    "kunyomi": [
      "いう",
      "い",
      "こと"
    ],
    "meaning_en": "",
    "meaning_hira": "",
    "label": "げん"
  },
  {
    "kanji": "原",
    "grade": 2,
    "kyoiku_index": 119,
    "onyomi": [
      "ゲン"
    ],
    "kunyomi": [
      "はら"
    ],
    "meaning_en": "",
    "meaning_hira": "",
    "label": "げん"
  },
  {
    "kanji": "戸",
    "grade": 2,
    "kyoiku_index": 120,
    "onyomi": [
      "コ"
    ],
    "kunyomi": [
      "と"
    ],
    "meaning_en": "",
    "meaning_hira": "",
    "label": "と"
  },
  {
    "kanji": "古",
    "grade": 2,
    "kyoiku_index": 121,
    "onyomi": [
      "コ"
    ],
    "kunyomi": [
      "ふるい",
      "ふる"
    ],
    "meaning_en": "",
    "meaning_hira": "",
    "label": "いにしえ"
  },
  {
    "kanji": "午",
    "grade": 2,
    "kyoiku_index": 122,
    "onyomi": [
      "ゴ"
    ],
    "kunyomi": [
      "うま"
    ],
    "meaning_en": "",
    "meaning_hira": "",
    "label": "[ご]"
  },
  {
    "kanji": "後",
    "grade": 2,
    "kyoiku_index": 123,
    "onyomi": [
      "ゴ",
      "コウ"
    ],
    "kunyomi": [
      "のち",
      "うし",
      "うしろ",
      "あと",
      "おく"
    ],
    "meaning_en": "",
    "meaning_hira": "",
    "label": "ご"
  },
  {
    "kanji": "語",
    "grade": 2,
    "kyoiku_index": 124,
    "onyomi": [
      "ゴ"
    ],
    "kunyomi": [
      "かたる",
      "かた"
    ],
    "meaning_en": "",
    "meaning_hira": "",
    "label": "ご"
  },
  {
    "kanji": "工",
    "grade": 2,
    "kyoiku_index": 125,
    "onyomi": [
      "コウ",
      "ク",
      "グ"
    ],
    "kunyomi": [],
    "meaning_en": "",
    "meaning_hira": "",
    "label": "こう"
  },
  {
    "kanji": "公",
    "grade": 2,
    "kyoiku_index": 126,
    "onyomi": [
      "コウ",
      "ク"
    ],
    "kunyomi": [
      "おおやけ"
    ],
    "meaning_en": "",
    "meaning_hira": "",
    "label": "きみ"
  },
  {
    "kanji": "広",
    "grade": 2,
    "kyoiku_index": 127,
    "onyomi": [
      "コウ"
    ],
    "kunyomi": [
      "ひろい",
      "ひろ"
    ],
    "meaning_en": "",
    "meaning_hira": "",
    "label": "[ひろ]い"
  },
  {
    "kanji": "交",
    "grade": 2,
    "kyoiku_index": 128,
    "onyomi": [
      "コウ"
    ],
    "kunyomi": [
      "まじわる",
      "まじ",
      "ま",
      "か",
      "かわ",
      "こもごも"
    ],
    "meaning_en": "",
    "meaning_hira": "",
    "label": "[か]わす"
  },
  {
    "kanji": "光",
    "grade": 2,
    "kyoiku_index": 129,
    "onyomi": [
      "コウ"
    ],
    "kunyomi": [
      "ひかる",
      "ひか",
      "ひかり"
    ],
    "meaning_en": "",
    "meaning_hira": "",
    "label": "ひかり"
  },
  {
    "kanji": "考",
    "grade": 2,
    "kyoiku_index": 130,
    "onyomi": [
      "コウ"
    ],
    "kunyomi": [
      "かんがえる",
      "かんが"
    ],
    "meaning_en": "",
    "meaning_hira": "",
    "label": "こう"
  },
  {
    "kanji": "行",
    "grade": 2,
    "kyoiku_index": 131,
    "onyomi": [
      "コウ",
      "ギョウ",
      "アン"
    ],
    "kunyomi": [
      "いく",
      "い",
      "ゆ",
      "おこな",
      "おこ"
    ],
    "meaning_en": "",
    "meaning_hira": "",
    "label": "ぎょう"
  },
  {
    "kanji": "高",
    "grade": 2,
    "kyoiku_index": 132,
    "onyomi": [
      "コウ"
    ],
    "kunyomi": [
      "たかい",
      "たか"
    ],
    "meaning_en": "",
    "meaning_hira": "",
    "label": "こう"
  },
  {
    "kanji": "黄",
    "grade": 2,
    "kyoiku_index": 133,
    "onyomi": [
      "コウ",
      "オウ"
    ],
    "kunyomi": [
      "き"
    ],
    "meaning_en": "",
    "meaning_hira": "",
    "label": "き"
  },
  {
    "kanji": "合",
    "grade": 2,
    "kyoiku_index": 134,
    "onyomi": [
      "ゴウ",
      "ガッ",
      "カッ"
    ],
    "kunyomi": [
      "あう",
      "あ"
    ],
    "meaning_en": "",
    "meaning_hira": "",
    "label": "あい"
  },
  {
    "kanji": "谷",
    "grade": 2,
    "kyoiku_index": 135,
    "onyomi": [
      "コク"
    ],
    "kunyomi": [
      "たに",
      "きわ"
    ],
    "meaning_en": "",
    "meaning_hira": "",
    "label": "たに"
  },
  {
    "kanji": "国",
    "grade": 2,
    "kyoiku_index": 136,
    "onyomi": [
      "コク"
    ],
    "kunyomi": [
      "くに"
    ],
    "meaning_en": "",
    "meaning_hira": "",
    "label": "くに"
  },
  {
    "kanji": "黒",
    "grade": 2,
    "kyoiku_index": 137,
    "onyomi": [
      "コク"
    ],
    "kunyomi": [
      "くろ"
    ],
    "meaning_en": "",
    "meaning_hira": "",
    "label": "くろ"
  },
  {
    "kanji": "今",
    "grade": 2,
    "kyoiku_index": 138,
    "onyomi": [
      "コン",
      "キン"
    ],
    "kunyomi": [
      "いま"
    ],
    "meaning_en": "",
    "meaning_hira": "",
    "label": "いま"
  },
  {
    "kanji": "才",
    "grade": 2,
    "kyoiku_index": 139,
    "onyomi": [
      "サイ"
    ],
    "kunyomi": [],
    "meaning_en": "",
    "meaning_hira": "",
    "label": "さい"
  },
  {
    "kanji": "細",
    "grade": 2,
    "kyoiku_index": 140,
    "onyomi": [
      "サイ"
    ],
    "kunyomi": [
      "ほそい",
      "ほそ",
      "こま"
    ],
    "meaning_en": "",
    "meaning_hira": "",
    "label": "さい"
  },
  {
    "kanji": "作",
    "grade": 2,
    "kyoiku_index": 141,
    "onyomi": [
      "サク",
      "サ"
    ],
    "kunyomi": [
      "つくる",
      "つく"
    ],
    "meaning_en": "",
    "meaning_hira": "",
    "label": "さく"
  },
  {
    "kanji": "算",
    "grade": 2,
    "kyoiku_index": 142,
    "onyomi": [
      "サン"
    ],
    "kunyomi": [
      "そろ"
    ],
    "meaning_en": "",
    "meaning_hira": "",
    "label": "[さん]"
  },
  {
    "kanji": "止",
    "grade": 2,
    "kyoiku_index": 143,
    "onyomi": [
      "シ"
    ],
    "kunyomi": [
      "とまる",
      "と",
      "とど",
      "や",
      "よ"
    ],
    "meaning_en": "",
    "meaning_hira": "",
    "label": "[とど]める"
  },
  {
    "kanji": "市",
    "grade": 2,
    "kyoiku_index": 144,
    "onyomi": [
      "シ"
    ],
    "kunyomi": [
      "いち"
    ],
    "meaning_en": "",
    "meaning_hira": "",
    "label": "いち"
  },
  {
    "kanji": "矢",
    "grade": 2,
    "kyoiku_index": 145,
    "onyomi": [
      "シ"
    ],
    "kunyomi": [
      "や"
    ],
    "meaning_en": "",
    "meaning_hira": "",
    "label": "や"
  },
  {
    "kanji": "姉",
    "grade": 2,
    "kyoiku_index": 146,
    "onyomi": [
      "シ"
    ],
    "kunyomi": [
      "あね",
      "はは"
    ],
    "meaning_en": "",
    "meaning_hira": "",
    "label": "あね"
  },
  {
    "kanji": "思",
    "grade": 2,
    "kyoiku_index": 147,
    "onyomi": [
      "シ"
    ],
    "kunyomi": [
      "おもう",
      "おも",
      "おもえら",
      "おぼ"
    ],
    "meaning_en": "",
    "meaning_hira": "",
    "label": "[おも]う"
  },
  {
    "kanji": "紙",
    "grade": 2,
    "kyoiku_index": 148,
    "onyomi": [
      "シ"
    ],
    "kunyomi": [
      "かみ"
    ],
    "meaning_en": "",
    "meaning_hira": "",
    "label": "し"
  },
  {
    "kanji": "寺",
    "grade": 2,
    "kyoiku_index": 149,
    "onyomi": [
      "ジ"
    ],
    "kunyomi": [
      "てら"
    ],
    "meaning_en": "",
    "meaning_hira": "",
    "label": "てら"
  },
  {
    "kanji": "自",
    "grade": 2,
    "kyoiku_index": 150,
    "onyomi": [
      "ジ",
      "シ"
    ],
    "kunyomi": [
      "みずから",
      "みずか",
      "おの"
    ],
    "meaning_en": "",
    "meaning_hira": "",
    "label": "じ"
  },
  {
    "kanji": "時",
    "grade": 2,
    "kyoiku_index": 151,
    "onyomi": [
      "ジ"
    ],
    "kunyomi": [
      "とき"
    ],
    "meaning_en": "",
    "meaning_hira": "",
    "label": "じ"
  },
  {
    "kanji": "室",
    "grade": 2,
    "kyoiku_index": 152,
    "onyomi": [
      "シツ"
    ],
    "kunyomi": [
      "むろ"
    ],
    "meaning_en": "",
    "meaning_hira": "",
    "label": "しつ"
  },
  {
    "kanji": "社",
    "grade": 2,
    "kyoiku_index": 153,
    "onyomi": [
      "シャ"
    ],
    "kunyomi": [
      "やしろ"
    ],
    "meaning_en": "",
    "meaning_hira": "",
    "label": "しゃ"
  },
  {
    "kanji": "弱",
    "grade": 2,
    "kyoiku_index": 154,
    "onyomi": [
      "ジャク"
    ],
    "kunyomi": [
      "よわい",
      "よわ"
    ],
    "meaning_en": "",
    "meaning_hira": "",
    "label": "じゃく"
  },
  {
    "kanji": "首",
    "grade": 2,
    "kyoiku_index": 155,
    "onyomi": [
      "シュ"
    ],
    "kunyomi": [
      "くび"
    ],
    "meaning_en": "",
    "meaning_hira": "",
    "label": "かしら"
  },
  {
    "kanji": "秋",
    "grade": 2,
    "kyoiku_index": 156,
    "onyomi": [
      "シュウ"
    ],
    "kunyomi": [
      "あき",
      "とき"
    ],
    "meaning_en": "",
    "meaning_hira": "",
    "label": "とき"
  },
  {
    "kanji": "週",
    "grade": 2,
    "kyoiku_index": 157,
    "onyomi": [
      "シュウ"
    ],
    "kunyomi": [],
    "meaning_en": "",
    "meaning_hira": "",
    "label": "しゅう"
  },
  {
    "kanji": "春",
    "grade": 2,
    "kyoiku_index": 158,
    "onyomi": [
      "シュン"
    ],
    "kunyomi": [
      "はる"
    ],
    "meaning_en": "",
    "meaning_hira": "",
    "label": "はる"
  },
  {
    "kanji": "書",
    "grade": 2,
    "kyoiku_index": 159,
    "onyomi": [
      "ショ"
    ],
    "kunyomi": [
      "かく",
      "か"
    ],
    "meaning_en": "",
    "meaning_hira": "",
    "label": "ふみ"
  },
  {
    "kanji": "少",
    "grade": 2,
    "kyoiku_index": 160,
    "onyomi": [
      "ショウ"
    ],
    "kunyomi": [
      "すくない",
      "すく",
      "すこ"
    ],
    "meaning_en": "",
    "meaning_hira": "",
    "label": "しょう"
  },
  {
    "kanji": "場",
    "grade": 2,
    "kyoiku_index": 161,
    "onyomi": [
      "ジョウ",
      "チョウ"
    ],
    "kunyomi": [
      "ば"
    ],
    "meaning_en": "",
    "meaning_hira": "",
    "label": "じょう"
  },
  {
    "kanji": "色",
    "grade": 2,
    "kyoiku_index": 162,
    "onyomi": [
      "ショク",
      "シキ"
    ],
    "kunyomi": [
      "いろ"
    ],
    "meaning_en": "",
    "meaning_hira": "",
    "label": "しょく"
  },
  {
    "kanji": "食",
    "grade": 2,
    "kyoiku_index": 163,
    "onyomi": [
      "ショク",
      "ジキ"
    ],
    "kunyomi": [
      "くう",
      "く",
      "た",
      "は"
    ],
    "meaning_en": "",
    "meaning_hira": "",
    "label": "しょく"
  },
  {
    "kanji": "心",
    "grade": 2,
    "kyoiku_index": 164,
    "onyomi": [
      "シン"
    ],
    "kunyomi": [
      "こころ"
    ],
    "meaning_en": "",
    "meaning_hira": "",
    "label": "しん"
  },
  {
    "kanji": "新",
    "grade": 2,
    "kyoiku_index": 165,
    "onyomi": [
      "シン"
    ],
    "kunyomi": [
      "あたらしい",
      "あたら",
      "あら"
    ],
    "meaning_en": "",
    "meaning_hira": "",
    "label": "さら"
  },
  {
    "kanji": "親",
    "grade": 2,
    "kyoiku_index": 166,
    "onyomi": [
      "シン"
    ],
    "kunyomi": [
      "おや",
      "した"
    ],
    "meaning_en": "",
    "meaning_hira": "",
    "label": "しん"
  },
  {
    "kanji": "図",
    "grade": 2,
    "kyoiku_index": 167,
    "onyomi": [
      "ズ",
      "ト"
    ],
    "kunyomi": [
      "え",
      "はか"
    ],
    "meaning_en": "",
    "meaning_hira": "",
    "label": "ず"
  },
  {
    "kanji": "数",
    "grade": 2,
    "kyoiku_index": 168,
    "onyomi": [
      "スウ",
      "ス",
      "サク",
      "ソク",
      "シュ"
    ],
    "kunyomi": [
      "かず",
      "かぞ",
      "しばしば",
      "せ",
      "わずらわ"
    ],
    "meaning_en": "",
    "meaning_hira": "",
    "label": "しばしば"
  },
  {
    "kanji": "西",
    "grade": 2,
    "kyoiku_index": 169,
    "onyomi": [
      "セイ",
      "サイ",
      "ス"
    ],
    "kunyomi": [
      "にし"
    ],
    "meaning_en": "",
    "meaning_hira": "",
    "label": "せい"
  },
  {
    "kanji": "声",
    "grade": 2,
    "kyoiku_index": 170,
    "onyomi": [
      "セイ",
      "ショウ"
    ],
    "kunyomi": [
      "こえ"
    ],
    "meaning_en": "",
    "meaning_hira": "",
    "label": "しょう"
  },
  {
    "kanji": "星",
    "grade": 2,
    "kyoiku_index": 171,
    "onyomi": [
      "セイ",
      "ショウ"
    ],
    "kunyomi": [
      "ほし"
    ],
    "meaning_en": "",
    "meaning_hira": "",
    "label": "せい"
  },
  {
    "kanji": "晴",
    "grade": 2,
    "kyoiku_index": 172,
    "onyomi": [
      "セイ"
    ],
    "kunyomi": [
      "はれる",
      "は"
    ],
    "meaning_en": "",
    "meaning_hira": "",
    "label": "はれ"
  },
  {
    "kanji": "切",
    "grade": 2,
    "kyoiku_index": 173,
    "onyomi": [
      "セツ",
      "サイ"
    ],
    "kunyomi": [
      "きる",
      "き"
    ],
    "meaning_en": "",
    "meaning_hira": "",
    "label": "せつ"
  },
  {
    "kanji": "雪",
    "grade": 2,
    "kyoiku_index": 174,
    "onyomi": [
      "セツ"
    ],
    "kunyomi": [
      "ゆき"
    ],
    "meaning_en": "",
    "meaning_hira": "",
    "label": "ゆき"
  },
  {
    "kanji": "船",
    "grade": 2,
    "kyoiku_index": 175,
    "onyomi": [
      "セン"
    ],
    "kunyomi": [
      "ふね"
    ],
    "meaning_en": "",
    "meaning_hira": "",
    "label": "せん"
  },
  {
    "kanji": "線",
    "grade": 2,
    "kyoiku_index": 176,
    "onyomi": [
      "セン"
    ],
    "kunyomi": [
      "すじ"
    ],
    "meaning_en": "",
    "meaning_hira": "",
    "label": "せん"
  },
  {
    "kanji": "前",
    "grade": 2,
    "kyoiku_index": 177,
    "onyomi": [
      "ゼン"
    ],
    "kunyomi": [
      "まえ"
    ],
    "meaning_en": "",
    "meaning_hira": "",
    "label": "さき"
  },
  {
    "kanji": "組",
    "grade": 2,
    "kyoiku_index": 178,
    "onyomi": [
      "ソ"
    ],
    "kunyomi": [
      "くむ",
      "く",
      "くみ"
    ],
    "meaning_en": "",
    "meaning_hira": "",
    "label": "くみ"
  },
  {
    "kanji": "走",
    "grade": 2,
    "kyoiku_index": 179,
    "onyomi": [
      "ソウ"
    ],
    "kunyomi": [
      "はしる",
      "はし"
    ],
    "meaning_en": "",
    "meaning_hira": "",
    "label": "[はし]る"
  },
  {
    "kanji": "多",
    "grade": 2,
    "kyoiku_index": 180,
    "onyomi": [
      "タ"
    ],
    "kunyomi": [
      "おおい",
      "おお",
      "まさ"
    ],
    "meaning_en": "",
    "meaning_hira": "",
    "label": "た"
  },
  {
    "kanji": "太",
    "grade": 2,
    "kyoiku_index": 181,
    "onyomi": [
      "タイ",
      "タ"
    ],
    "kunyomi": [
      "ふとい",
      "ふと"
    ],
    "meaning_en": "",
    "meaning_hira": "",
    "label": "ふと"
  },
  {
    "kanji": "体",
    "grade": 2,
    "kyoiku_index": 182,
    "onyomi": [
      "タイ",
      "テイ"
    ],
    "kunyomi": [
      "からだ",
      "かたち"
    ],
    "meaning_en": "",
    "meaning_hira": "",
    "label": "からだ"
  },
  {
    "kanji": "台",
    "grade": 2,
    "kyoiku_index": 183,
    "onyomi": [
      "ダイ",
      "タイ"
    ],
    "kunyomi": [
      "うてな",
      "われ",
      "つかさ"
    ],
    "meaning_en": "",
    "meaning_hira": "",
    "label": "だい"
  },
  {
    "kanji": "地",
    "grade": 2,
    "kyoiku_index": 184,
    "onyomi": [
      "チ",
      "ジ"
    ],
    "kunyomi": [],
    "meaning_en": "",
    "meaning_hira": "",
    "label": "ち"
  },
  {
    "kanji": "池",
    "grade": 2,
    "kyoiku_index": 185,
    "onyomi": [
      "チ"
    ],
    "kunyomi": [
      "いけ"
    ],
    "meaning_en": "",
    "meaning_hira": "",
    "label": "いけ"
  },
  {
    "kanji": "知",
    "grade": 2,
    "kyoiku_index": 186,
    "onyomi": [
      "チ"
    ],
    "kunyomi": [
      "しる",
      "し"
    ],
    "meaning_en": "",
    "meaning_hira": "",
    "label": "ち"
  },
  {
    "kanji": "茶",
    "grade": 2,
    "kyoiku_index": 187,
    "onyomi": [
      "チャ",
      "サ"
    ],
    "kunyomi": [],
    "meaning_en": "",
    "meaning_hira": "",
    "label": "ちゃ"
  },
  {
    "kanji": "昼",
    "grade": 2,
    "kyoiku_index": 188,
    "onyomi": [
      "チュウ"
    ],
    "kunyomi": [
      "ひる"
    ],
    "meaning_en": "",
    "meaning_hira": "",
    "label": "ひる"
  },
  {
    "kanji": "長",
    "grade": 2,
    "kyoiku_index": 189,
    "onyomi": [
      "チョウ"
    ],
    "kunyomi": [
      "ながい",
      "なが",
      "おさ"
    ],
    "meaning_en": "",
    "meaning_hira": "",
    "label": "ちょう"
  },
  {
    "kanji": "鳥",
    "grade": 2,
    "kyoiku_index": 190,
    "onyomi": [
      "チョウ"
    ],
    "kunyomi": [
      "とり"
    ],
    "meaning_en": "",
    "meaning_hira": "",
    "label": "とり"
  },
  {
    "kanji": "朝",
    "grade": 2,
    "kyoiku_index": 191,
    "onyomi": [
      "チョウ"
    ],
    "kunyomi": [
      "あさ"
    ],
    "meaning_en": "",
    "meaning_hira": "",
    "label": "あさ"
  },
  {
    "kanji": "直",
    "grade": 2,
    "kyoiku_index": 192,
    "onyomi": [
      "チョク",
      "ジキ",
      "ジカ"
    ],
    "kunyomi": [
      "ただちに",
      "ただ",
      "なお",
      "す"
    ],
    "meaning_en": "",
    "meaning_hira": "",
    "label": "なお"
  },
  {
    "kanji": "通",
    "grade": 2,
    "kyoiku_index": 193,
    "onyomi": [
      "ツウ",
      "ツ"
    ],
    "kunyomi": [
      "とおる",
      "とお",
      "かよ"
    ],
    "meaning_en": "",
    "meaning_hira": "",
    "label": "つう"
  },
  {
    "kanji": "弟",
    "grade": 2,
    "kyoiku_index": 194,
    "onyomi": [
      "テイ",
      "ダイ",
      "デ"
    ],
    "kunyomi": [
      "おとうと"
    ],
    "meaning_en": "",
    "meaning_hira": "",
    "label": "おとうと"
  },
  {
    "kanji": "店",
    "grade": 2,
    "kyoiku_index": 195,
    "onyomi": [
      "テン"
    ],
    "kunyomi": [
      "みせ",
      "たな"
    ],
    "meaning_en": "",
    "meaning_hira": "",
    "label": "たな"
  },
  {
    "kanji": "点",
    "grade": 2,
    "kyoiku_index": 196,
    "onyomi": [
      "テン"
    ],
    "kunyomi": [
      "つける",
      "つ",
      "た",
      "さ",
      "とぼ",
      "とも",
      "ぼち"
    ],
    "meaning_en": "",
    "meaning_hira": "",
    "label": "ちょぼ"
  },
  {
    "kanji": "電",
    "grade": 2,
    "kyoiku_index": 197,
    "onyomi": [
      "デン"
    ],
    "kunyomi": [],
    "meaning_en": "",
    "meaning_hira": "",
    "label": "いなずま"
  },
  {
    "kanji": "刀",
    "grade": 2,
    "kyoiku_index": 198,
    "onyomi": [
      "トウ"
    ],
    "kunyomi": [
      "かたな",
      "そり"
    ],
    "meaning_en": "",
    "meaning_hira": "",
    "label": "かたな"
  },
  {
    "kanji": "冬",
    "grade": 2,
    "kyoiku_index": 199,
    "onyomi": [
      "トウ"
    ],
    "kunyomi": [
      "ふゆ"
    ],
    "meaning_en": "",
    "meaning_hira": "",
    "label": "ふゆ"
  },
  {
    "kanji": "当",
    "grade": 2,
    "kyoiku_index": 200,
    "onyomi": [
      "トウ"
    ],
    "kunyomi": [
      "あたる",
      "あ",
      "まさ"
    ],
    "meaning_en": "",
    "meaning_hira": "",
    "label": "はた"
  },
  {
    "kanji": "東",
    "grade": 2,
    "kyoiku_index": 201,
    "onyomi": [
      "トウ"
    ],
    "kunyomi": [
      "ひがし"
    ],
    "meaning_en": "",
    "meaning_hira": "",
    "label": "あずま"
  },
  {
    "kanji": "答",
    "grade": 2,
    "kyoiku_index": 202,
    "onyomi": [
      "トウ"
    ],
    "kunyomi": [
      "こたえる",
      "こた"
    ],
    "meaning_en": "",
    "meaning_hira": "",
    "label": "こたえ"
  },
  {
    "kanji": "頭",
    "grade": 2,
    "kyoiku_index": 203,
    "onyomi": [
      "トウ",
      "ズ",
      "ト"
    ],
    "kunyomi": [
      "あたま",
      "かしら",
      "かぶり"
    ],
    "meaning_en": "",
    "meaning_hira": "",
    "label": "かぶし"
  },
  {
    "kanji": "同",
    "grade": 2,
    "kyoiku_index": 204,
    "onyomi": [
      "ドウ"
    ],
    "kunyomi": [
      "おなじ",
      "おな"
    ],
    "meaning_en": "",
    "meaning_hira": "",
    "label": "どう"
  },
  {
    "kanji": "道",
    "grade": 2,
    "kyoiku_index": 205,
    "onyomi": [
      "ドウ",
      "トウ"
    ],
    "kunyomi": [
      "みち",
      "いう"
    ],
    "meaning_en": "",
    "meaning_hira": "",
    "label": "どう"
  },
  {
    "kanji": "読",
    "grade": 2,
    "kyoiku_index": 206,
    "onyomi": [
      "ドク",
      "トク",
      "トウ"
    ],
    "kunyomi": [
      "よむ",
      "よ"
    ],
    "meaning_en": "",
    "meaning_hira": "",
    "label": "[よ]む"
  },
  {
    "kanji": "内",
    "grade": 2,
    "kyoiku_index": 207,
    "onyomi": [
      "ナイ",
      "ダイ"
    ],
    "kunyomi": [
      "うち"
    ],
    "meaning_en": "",
    "meaning_hira": "",
    "label": "うち"
  },
  {
    "kanji": "南",
    "grade": 2,
    "kyoiku_index": 208,
    "onyomi": [
      "ナン",
      "ナ"
    ],
    "kunyomi": [
      "みなみ"
    ],
    "meaning_en": "",
    "meaning_hira": "",
    "label": "みなみ"
  },
  {
    "kanji": "肉",
    "grade": 2,
    "kyoiku_index": 209,
    "onyomi": [
      "ニク"
    ],
    "kunyomi": [
      "しし"
    ],
    "meaning_en": "",
    "meaning_hira": "",
    "label": "にく"
  },
  {
    "kanji": "馬",
    "grade": 2,
    "kyoiku_index": 210,
    "onyomi": [
      "バ"
    ],
    "kunyomi": [
      "うま",
      "ま"
    ],
    "meaning_en": "",
    "meaning_hira": "",
    "label": "うま"
  },
  {
    "kanji": "売",
    "grade": 2,
    "kyoiku_index": 211,
    "onyomi": [
      "バイ"
    ],
    "kunyomi": [
      "うる",
      "う"
    ],
    "meaning_en": "",
    "meaning_hira": "",
    "label": "[う]る"
  },
  {
    "kanji": "買",
    "grade": 2,
    "kyoiku_index": 212,
    "onyomi": [
      "バイ"
    ],
    "kunyomi": [
      "かう",
      "か"
    ],
    "meaning_en": "",
    "meaning_hira": "",
    "label": "[か]う"
  },
  {
    "kanji": "麦",
    "grade": 2,
    "kyoiku_index": 213,
    "onyomi": [
      "バク"
    ],
    "kunyomi": [
      "むぎ"
    ],
    "meaning_en": "",
    "meaning_hira": "",
    "label": "むぎ"
  },
  {
    "kanji": "半",
    "grade": 2,
    "kyoiku_index": 214,
    "onyomi": [
      "ハン"
    ],
    "kunyomi": [
      "なかば",
      "なか"
    ],
    "meaning_en": "",
    "meaning_hira": "",
    "label": "はん"
  },
  {
    "kanji": "番",
    "grade": 2,
    "kyoiku_index": 215,
    "onyomi": [
      "バン"
    ],
    "kunyomi": [
      "つがい",
      "つが"
    ],
    "meaning_en": "",
    "meaning_hira": "",
    "label": "つがい"
  },
  {
    "kanji": "父",
    "grade": 2,
    "kyoiku_index": 216,
    "onyomi": [
      "フ"
    ],
    "kunyomi": [
      "ちち"
    ],
    "meaning_en": "",
    "meaning_hira": "",
    "label": "ちち"
  },
  {
    "kanji": "風",
    "grade": 2,
    "kyoiku_index": 217,
    "onyomi": [
      "フウ",
      "フ"
    ],
    "kunyomi": [
      "かぜ"
    ],
    "meaning_en": "",
    "meaning_hira": "",
    "label": "かぜ"
  },
  {
    "kanji": "分",
    "grade": 2,
    "kyoiku_index": 218,
    "onyomi": [
      "ブン",
      "フン",
      "ブ"
    ],
    "kunyomi": [
      "わける",
      "わ"
    ],
    "meaning_en": "",
    "meaning_hira": "",
    "label": "ふん"
  },
  {
    "kanji": "聞",
    "grade": 2,
    "kyoiku_index": 219,
    "onyomi": [
      "ブン",
      "モン"
    ],
    "kunyomi": [
      "きく",
      "き"
    ],
    "meaning_en": "",
    "meaning_hira": "",
    "label": "[き]く"
  },
  {
    "kanji": "米",
    "grade": 2,
    "kyoiku_index": 220,
    "onyomi": [
      "ベイ",
      "マイ",
      "メエトル"
    ],
    "kunyomi": [
      "こめ",
      "よね"
    ],
    "meaning_en": "",
    "meaning_hira": "",
    "label": "べい"
  },
  {
    "kanji": "歩",
    "grade": 2,
    "kyoiku_index": 221,
    "onyomi": [
      "ホ",
      "ブ",
      "フ"
    ],
    "kunyomi": [
      "あるく",
      "ある",
      "あゆ"
    ],
    "meaning_en": "",
    "meaning_hira": "",
    "label": "ぶ"
  },
  {
    "kanji": "母",
    "grade": 2,
    "kyoiku_index": 222,
    "onyomi": [
      "ボ"
    ],
    "kunyomi": [
      "はは",
      "も"
    ],
    "meaning_en": "",
    "meaning_hira": "",
    "label": "はは"
  },
  {
    "kanji": "方",
    "grade": 2,
    "kyoiku_index": 223,
    "onyomi": [
      "ホウ"
    ],
    "kunyomi": [
      "かた"
    ],
    "meaning_en": "",
    "meaning_hira": "",
    "label": "かた"
  },
  {
    "kanji": "北",
    "grade": 2,
    "kyoiku_index": 224,
    "onyomi": [
      "ホク"
    ],
    "kunyomi": [
      "きた"
    ],
    "meaning_en": "",
    "meaning_hira": "",
    "label": "きた"
  },
  {
    "kanji": "毎",
    "grade": 2,
    "kyoiku_index": 225,
    "onyomi": [
      "マイ"
    ],
    "kunyomi": [
      "ごと"
    ],
    "meaning_en": "",
    "meaning_hira": "",
    "label": "ごと"
  },
  {
    "kanji": "妹",
    "grade": 2,
    "kyoiku_index": 226,
    "onyomi": [
      "マイ"
    ],
    "kunyomi": [
      "いもうと"
    ],
    "meaning_en": "",
    "meaning_hira": "",
    "label": "いも"
  },
  {
    "kanji": "万",
    "grade": 2,
    "kyoiku_index": 227,
    "onyomi": [
      "マン",
      "バン"
    ],
    "kunyomi": [
      "よろず"
    ],
    "meaning_en": "",
    "meaning_hira": "",
    "label": "まん"
  },
  {
    "kanji": "明",
    "grade": 2,
    "kyoiku_index": 228,
    "onyomi": [
      "メイ",
      "ミョウ",
      "ミン"
    ],
    "kunyomi": [
      "あかり",
      "あ",
      "あか",
      "あき"
    ],
    "meaning_en": "",
    "meaning_hira": "",
    "label": "みょう"
  },
  {
    "kanji": "鳴",
    "grade": 2,
    "kyoiku_index": 229,
    "onyomi": [
      "メイ"
    ],
    "kunyomi": [
      "なく",
      "な"
    ],
    "meaning_en": "",
    "meaning_hira": "",
    "label": "[な]る"
  },
  {
    "kanji": "毛",
    "grade": 2,
    "kyoiku_index": 230,
    "onyomi": [
      "モウ"
    ],
    "kunyomi": [
      "け"
    ],
    "meaning_en": "",
    "meaning_hira": "",
    "label": "もう"
  },
  {
    "kanji": "門",
    "grade": 2,
    "kyoiku_index": 231,
    "onyomi": [
      "モン"
    ],
    "kunyomi": [
      "かど",
      "と"
    ],
    "meaning_en": "",
    "meaning_hira": "",
    "label": "と"
  },
  {
    "kanji": "夜",
    "grade": 2,
    "kyoiku_index": 232,
    "onyomi": [
      "ヤ"
    ],
    "kunyomi": [
      "よ",
      "よる"
    ],
    "meaning_en": "",
    "meaning_hira": "",
    "label": "や"
  },
  {
    "kanji": "野",
    "grade": 2,
    "kyoiku_index": 233,
    "onyomi": [
      "ヤ",
      "ショ"
    ],
    "kunyomi": [
      "の"
    ],
    "meaning_en": "",
    "meaning_hira": "",
    "label": "の"
  },
  {
    "kanji": "友",
    "grade": 2,
    "kyoiku_index": 234,
    "onyomi": [
      "ユウ"
    ],
    "kunyomi": [
      "とも"
    ],
    "meaning_en": "",
    "meaning_hira": "",
    "label": "とも"
  },
  {
    "kanji": "用",
    "grade": 2,
    "kyoiku_index": 235,
    "onyomi": [
      "ヨウ"
    ],
    "kunyomi": [
      "もちいる",
      "もち"
    ],
    "meaning_en": "",
    "meaning_hira": "",
    "label": "よう"
  },
  {
    "kanji": "曜",
    "grade": 2,
    "kyoiku_index": 236,
    "onyomi": [
      "ヨウ"
    ],
    "kunyomi": [],
    "meaning_en": "",
    "meaning_hira": "",
    "label": "[よう]"
  },
  {
    "kanji": "来",
    "grade": 2,
    "kyoiku_index": 237,
    "onyomi": [
      "ライ",
      "タイ"
    ],
    "kunyomi": [
      "くる",
      "く",
      "きた",
      "き",
      "こ"
    ],
    "meaning_en": "",
    "meaning_hira": "",
    "label": "らい"
  },
  {
    "kanji": "里",
    "grade": 2,
    "kyoiku_index": 238,
    "onyomi": [
      "リ"
    ],
    "kunyomi": [
      "さと"
    ],
    "meaning_en": "",
    "meaning_hira": "",
    "label": "さと"
  },
  {
    "kanji": "理",
    "grade": 2,
    "kyoiku_index": 239,
    "onyomi": [
      "リ"
    ],
    "kunyomi": [
      "ことわり"
    ],
    "meaning_en": "",
    "meaning_hira": "",
    "label": "ことわり"
  },
  {
    "kanji": "話",
    "grade": 2,
    "kyoiku_index": 240,
    "onyomi": [
      "ワ"
    ],
    "kunyomi": [
      "はなす",
      "はな",
      "はなし"
    ],
    "meaning_en": "",
    "meaning_hira": "",
    "label": "はなし"
  }
]
